barndoor/sdk/__init__.py
barndoor/sdk/_http.py
barndoor/sdk/auth.py
barndoor/sdk/auth_store.py
barndoor/sdk/cli_login.py
barndoor/sdk/client.py
barndoor/sdk/config.py
barndoor/sdk/exceptions.py
barndoor/sdk/logging.py
barndoor/sdk/models.py
barndoor/sdk/quickstart.py
barndoor/sdk/utils.py
barndoor/sdk/validation.py
barndoor/sdk/docs/openapi.yaml
barndoor-0.3.0.dist-info/METADATA
barndoor-0.3.0.dist-info/WHEEL
barndoor-0.3.0.dist-info/entry_points.txt
barndoor-0.3.0.dist-info/licenses/LICENSE
barndoor-0.3.0.dist-info/RECORD
