Metadata-Version: 2.4
Name: barndoor
Version: 0.3.0
Summary: Official Python SDK for the Barndoor API.
Author: Barndoor AI, Inc.
License: MIT
License-File: LICENSE
Keywords: ai,barndoor,mcp,sdk
Requires-Python: <4.0,>=3.10
Requires-Dist: httpx[http2]>=0.27.2
Requires-Dist: pydantic>=2.10.6
Requires-Dist: python-dotenv>=1.0.0
Requires-Dist: python-jose[cryptography]>=3.3.0
Requires-Dist: typing-extensions>=4.12.2
Provides-Extra: examples
Requires-Dist: crewai-tools>=0.1.0; extra == 'examples'
Requires-Dist: crewai>=0.30.0; extra == 'examples'
Requires-Dist: langchain-mcp-adapters; extra == 'examples'
Requires-Dist: langchain-openai; extra == 'examples'
Requires-Dist: langgraph>=0.5.3; extra == 'examples'
Requires-Dist: llama-index; extra == 'examples'
Requires-Dist: llama-index-tools-mcp; extra == 'examples'
Requires-Dist: openai>=1.61.1; extra == 'examples'
